rils/__init__.py
rils/node.py
rils/rils.py
rils/rils_ensemble.py
rils/rils_pipeline.py
rils/simplify_approx.py
rils/solution.py
rils/utils.py
rils-0.4.dist-info/METADATA
rils-0.4.dist-info/WHEEL
rils-0.4.dist-info/top_level.txt
rils-0.4.dist-info/RECORD
