Metadata-Version: 2.1
Name: rils
Version: 0.4
Summary: Regression via Iterated Local Search for Symbolic Regression GECCO Competition -- 2023
Home-page: https://github.com/kartelj/rils
Author: Aleksandar Kartelj, Marko Đukanović
Author-email: aleksandar.kartelj@gmail.com
Classifier: Programming Language :: Python :: 3
Classifier: License :: OSI Approved :: MIT License
Classifier: Operating System :: OS Independent
Requires-Python: >=3.6
Requires-Dist: numpy
Requires-Dist: sympy
Requires-Dist: scikit-learn
Requires-Dist: statsmodels
